design.v
// Code your design here
// Single Port RAM module design

module single_port_ram(
  input [7:0] data, //input data
  input [5:0] addr, //address
  input we, //write enable
  input clk, //clk
  output [7:0] q //output data
);
  
  reg [7:0] ram [63:0]; //8*64 bit ram
  reg [5:0] addr_reg; //address register
 
  always @ (posedge clk)
    begin
      if(we)
        ram[addr] <= data;
      else
        addr_reg <= addr; 
    end
 
  assign q = ram[addr_reg];
  
endmodule

testbench.v
// Code your testbench here
// or browse Examples
// Single Port RAM testbench

module single_port_ram_tb;
  reg [7:0] data; //input data
  reg [5:0] addr; //address
  reg we; //write enable
  reg clk; //clk
  wire [7:0] q; //output data 	
  
  single_port_ram spr1(
    .data(data),
    .addr(addr),
    .we(we),
    .clk(clk),
    .q(q)
  );
  
  initial
    begin
      $dumpfile("dump.vcd");
      $dumpvars(1, single_port_ram_tb);       
      
      clk=1'b1;
      forever #5 clk = ~clk;
    end
  
  initial
    begin
      data = 8'h01;
      addr = 5'd0;
      we = 1'b1;
      #10;
           
	  data = 8'h02;
      addr = 5'd1;     
      #10;
      
      data = 8'h03;
      addr = 5'd2;     
      #10;
      
      addr = 5'd0;
      we = 1'b0;
      #10;
      
      addr = 5'd1;
      #10;
      
      addr = 5'd2;
      #10;
      
      data = 8'h04;
      addr = 5'd1;
      we = 1'b1;
      #10;
      
      addr = 5'd1;
      we = 1'b0;
      #10;
      
      addr = 5'd3;
      #10;
    end
  
  initial
    #90 $stop;
  
endmodule

dump.vcd
$date
Tue Aug 27 10:37:23 2024
$end
$version
Riviera-PRO Version 2023.04.112.8911
$end
$timescale
1 ns
$end

$scope module single_port_ram_tb $end
$var wire 8 ! q [7:0] $end
$var reg 8 " data [7:0] $end
$var reg 6 # addr [5:0] $end
$var reg 1 $ we $end
$var reg 1 % clk $end
$upscope $end

$enddefinitions $end
$dumpvars
bx !
b1 "
b0 #
1$
1%
$end
#5
0%
#10
b10 "
b1 #
1%
#15
0%
#20
b11 "
b10 #
1%
#25
0%
#30
b0 #
0$
1%
b1 !
#35
0%
#40
b1 #
1%
b10 !
#45
0%
#50
b10 #
1%
b11 !
#55
0%
#60
b100 "
b1 #
1$
1%
#65
0%
#70
0$
1%
b100 !
#75
0%
#80
b11 #
1%
bx !
